PDBCOCO/__init__.py
PDBCOCO-0.2.dist-info/LICENSE
PDBCOCO-0.2.dist-info/METADATA
PDBCOCO-0.2.dist-info/WHEEL
PDBCOCO-0.2.dist-info/top_level.txt
PDBCOCO-0.2.dist-info/RECORD
