Metadata-Version: 2.1
Name: PDBCOCO
Version: 0.2
Summary: correcting errors in PDB files
Home-page: https://github.com/jordan078/PDBCOCO
Author: Jordan Yang
Author-email: haobo_yang@brown.edu
License: Brown
Platform: UNKNOWN
